sspipeline/__init__.py
sspipeline/cli.py
sspipeline/core.py
sspipeline/distributions.py
sspipeline/gelman_rubin.py
sspipeline/utils.py
sspipeline/version.py
sspipeline-0.1.0.dev0.dist-info/METADATA
sspipeline-0.1.0.dev0.dist-info/RECORD
sspipeline-0.1.0.dev0.dist-info/WHEEL
sspipeline-0.1.0.dev0.dist-info/entry_points.txt
sspipeline-0.1.0.dev0.dist-info/top_level.txt
