Metadata-Version: 2.1
Name: sspipeline
Version: 0.1.0.dev0
Summary: A pipeline for estimating and characterizing uncertainty in coastal storm surge levels
Home-page: https://github.com/MUSSLES/sspipeline
Author: John Letey
Author-email: john.letey@colorado.edu
License: GPLv3
Platform: UNKNOWN
